bitpredict/__init__.py
bitpredict/api.py
python_bitpredict-1.4.dist-info/LICENSE.txt
python_bitpredict-1.4.dist-info/METADATA
python_bitpredict-1.4.dist-info/WHEEL
python_bitpredict-1.4.dist-info/top_level.txt
python_bitpredict-1.4.dist-info/RECORD
