Metadata-Version: 2.1
Name: python-bitpredict
Version: 1.4
Summary: This package for serving api's in python
Author: Bitpredict
Author-email: admin@bitpredict.com
Classifier: Programming Language :: Python :: 3
Classifier: License :: OSI Approved :: MIT License
Classifier: Operating System :: OS Independent
License-File: LICENSE.txt
